constellaration/__about__.py
constellaration/__init__.py
constellaration/forward_model.py
constellaration/initial_guess.py
constellaration/problems.py
constellaration/boozer/__init__.py
constellaration/boozer/boozer.py
constellaration/data_generation/__init__.py
constellaration/data_generation/desc_optimization.py
constellaration/data_generation/desc_optimization_settings.py
constellaration/data_generation/rotational_transform_scaling.py
constellaration/data_generation/vmec_optimization.py
constellaration/data_generation/vmec_optimization_settings.py
constellaration/generative_model/bootstrap_dataset.py
constellaration/generative_model/mcmc_algo.py
constellaration/generative_model/optimize_with_mcmc.py
constellaration/geometry/__init__.py
constellaration/geometry/radial_profile.py
constellaration/geometry/surface_rz_fourier.py
constellaration/geometry/surface_utils.py
constellaration/geometry/surface_utils_desc.py
constellaration/mhd/__init__.py
constellaration/mhd/flux_power_series.py
constellaration/mhd/geometry_utils.py
constellaration/mhd/ideal_mhd_parameters.py
constellaration/mhd/ideal_mhd_parameters_utils.py
constellaration/mhd/magnetics_utils.py
constellaration/mhd/near_axis_configuration.py
constellaration/mhd/turbulent_transport.py
constellaration/mhd/vmec_settings.py
constellaration/mhd/vmec_utils.py
constellaration/omnigeneity/__init__.py
constellaration/omnigeneity/omnigenity_field.py
constellaration/omnigeneity/omnigenity_field_desc.py
constellaration/omnigeneity/omnigenity_field_plot.py
constellaration/omnigeneity/omnigenity_field_sampling.py
constellaration/omnigeneity/qi.py
constellaration/optimization/__init__.py
constellaration/optimization/augmented_lagrangian.py
constellaration/optimization/augmented_lagrangian_runner.py
constellaration/optimization/scipy_minimize_runner.py
constellaration/optimization/settings.py
constellaration/utils/__init__.py
constellaration/utils/dataset_utils.py
constellaration/utils/file_exporter.py
constellaration-0.2.5.dist-info/METADATA
constellaration-0.2.5.dist-info/WHEEL
constellaration-0.2.5.dist-info/licenses/LICENSE
constellaration-0.2.5.dist-info/RECORD
