Metadata-Version: 2.4
Name: constellaration
Version: 0.2.5
Summary: Code for analyzing and evaluating stellarator plasma shapes
Project-URL: Documentation, https://github.com/proximafusion/constellaration#readme
Project-URL: Issues, https://github.com/proximafusion/constellaration/issues
Project-URL: Source, https://github.com/proximafusion/constellaration
Author-email: Maria Pascu <mariap@proximafusion.com>
License-Expression: MIT
License-File: LICENSE
Classifier: Development Status :: 4 - Beta
Classifier: Programming Language :: Python
Classifier: Programming Language :: Python :: 3.10
Classifier: Programming Language :: Python :: 3.11
Classifier: Programming Language :: Python :: 3.12
Classifier: Programming Language :: Python :: Implementation :: CPython
Classifier: Programming Language :: Python :: Implementation :: PyPy
Requires-Python: >=3.10
Requires-Dist: booz-xform==0.0.9
Requires-Dist: datasets==3.5.1
Requires-Dist: desc-opt
Requires-Dist: interpax==0.3.8
Requires-Dist: ipykernel
Requires-Dist: ipython
Requires-Dist: jax<=0.6.0
Requires-Dist: jaxtyping
Requires-Dist: kaleido
Requires-Dist: matplotlib==3.9.2
Requires-Dist: nbformat
Requires-Dist: nevergrad
Requires-Dist: numpy>=2.1.3
Requires-Dist: orjson==3.10.16
Requires-Dist: pandas==2.2.3
Requires-Dist: plotly<7.0.0
Requires-Dist: pybind11<3.0.0
Requires-Dist: pydantic
Requires-Dist: pymoo==0.6.1.5
Requires-Dist: qicna==0.3.4
Requires-Dist: scikit-activeml==0.5.2
Requires-Dist: scikit-build-core==0.10
Requires-Dist: scikit-learn==1.5.2
Requires-Dist: scipy
Requires-Dist: seaborn==0.13.2
Requires-Dist: simsopt==1.8.1; python_version < '3.13'
Requires-Dist: simsopt==1.9.0; python_version >= '3.13'
Requires-Dist: vmecpp==0.4.11
Provides-Extra: lint
Requires-Dist: pre-commit; extra == 'lint'
Provides-Extra: test
Requires-Dist: pytest; extra == 'test'
